fastalite/__init__.py
fastalite/__main__.py
fastalite/fastalite.py
fastalite/data/ver
fastalite-0.3.dist-info/DESCRIPTION.rst
fastalite-0.3.dist-info/METADATA
fastalite-0.3.dist-info/RECORD
fastalite-0.3.dist-info/WHEEL
fastalite-0.3.dist-info/metadata.json
fastalite-0.3.dist-info/top_level.txt
tests/__init__.py
tests/test.py
