Metadata-Version: 2.0
Name: fastalite
Version: 0.3
Summary: Simplest possible fasta parser
Home-page: https://github.com/nhoffman/fastalite
Author: Noah Hoffman
Author-email: noah.hoffman@gmail.com
License: UNKNOWN
Platform: UNKNOWN
Classifier: Development Status :: 4 - Beta
Classifier: Intended Audience :: Developers
Classifier: Operating System :: POSIX
Classifier: Programming Language :: Python :: 2.7
Classifier: Programming Language :: Python :: 3.3
Classifier: Programming Language :: Python :: 3.4
Classifier: Programming Language :: Python :: 3.5
Classifier: Programming Language :: Python :: 3.6
